{
  "status": "ok",
  "generated_at": "2026-05-10T19:45:57.217257Z",
  "purge_rows": 6,
  "embargo_rows": 6,
  "folds": [
    {
      "fold": 0,
      "train_rows": 900,
      "test_rows": 5782,
      "train_end": 900,
      "test_start": 912,
      "test_end": 6694,
      "train_start_ts": "2026-01-07 03:00:00+00:00",
      "train_end_ts": "2026-01-10 05:55:00+00:00",
      "test_start_ts": "2026-01-10 07:00:00+00:00",
      "test_end_ts": "2026-01-30 08:45:00+00:00",
      "auc": 0.7314,
      "accuracy": 0.6707,
      "vol_mae": 0.002873,
      "vol_r2": 0.0453,
      "sharpe_ratio": -3.059,
      "total_return_pct": -0.069,
      "max_drawdown_pct": -0.139,
      "total_trades": 282,
      "mtf_gate_fired": 1834,
      "regime_breakdown": {
        "0": {
          "regime_id": 0,
          "candles": 3216,
          "trades": 39,
          "buys": 23,
          "sells": 16,
          "notional_usd": 501.95,
          "fees_usd": 0.8031,
          "penalty_usd": 0.3128,
          "trade_rate": 0.0121,
          "mean_stress": 0.0,
          "mean_trend_score": -0.0765,
          "mean_dir_proba": 0.44,
          "model_accuracy": 0.6717,
          "model_predictions": 1642,
          "avg_signed_return_bps": -5.4295
        },
        "3": {
          "regime_id": 3,
          "candles": 604,
          "trades": 88,
          "buys": 7,
          "sells": 81,
          "notional_usd": 980.32,
          "fees_usd": 1.5685,
          "penalty_usd": 1.1604,
          "trade_rate": 0.1457,
          "mean_stress": 0.3333,
          "mean_trend_score": -0.696,
          "mean_dir_proba": 0.494,
          "model_accuracy": 0.6592,
          "model_predictions": 223,
          "avg_signed_return_bps": -5.1431
        },
        "2": {
          "regime_id": 2,
          "candles": 1400,
          "trades": 44,
          "buys": 31,
          "sells": 13,
          "notional_usd": 541.28,
          "fees_usd": 0.866,
          "penalty_usd": 0.4995,
          "trade_rate": 0.0314,
          "mean_stress": 0.6667,
          "mean_trend_score": -0.2106,
          "mean_dir_proba": 0.5397,
          "model_accuracy": 0.6525,
          "model_predictions": 777,
          "avg_signed_return_bps": -5.1098
        },
        "1": {
          "regime_id": 1,
          "candles": 562,
          "trades": 111,
          "buys": 70,
          "sells": 41,
          "notional_usd": 1514.06,
          "fees_usd": 2.4225,
          "penalty_usd": 1.6241,
          "trade_rate": 0.1975,
          "mean_stress": 1.0,
          "mean_trend_score": 0.0027,
          "mean_dir_proba": 0.5393,
          "model_accuracy": 0.6072,
          "model_predictions": 359,
          "avg_signed_return_bps": 4.1435
        }
      }
    },
    {
      "fold": 1,
      "train_rows": 6682,
      "test_rows": 5782,
      "train_end": 6682,
      "test_start": 6694,
      "test_end": 12476,
      "train_start_ts": "2026-01-07 03:00:00+00:00",
      "train_end_ts": "2026-01-30 07:45:00+00:00",
      "test_start_ts": "2026-01-30 08:50:00+00:00",
      "test_end_ts": "2026-02-19 10:35:00+00:00",
      "auc": 0.7791,
      "accuracy": 0.6994,
      "vol_mae": 0.004414,
      "vol_r2": 0.1038,
      "sharpe_ratio": -8.182,
      "total_return_pct": -0.274,
      "max_drawdown_pct": -0.284,
      "total_trades": 919,
      "mtf_gate_fired": 1335,
      "regime_breakdown": {
        "0": {
          "regime_id": 0,
          "candles": 1968,
          "trades": 235,
          "buys": 120,
          "sells": 115,
          "notional_usd": 3282.47,
          "fees_usd": 5.252,
          "penalty_usd": 3.752,
          "trade_rate": 0.1194,
          "mean_stress": 0.6667,
          "mean_trend_score": 0.0169,
          "mean_dir_proba": 0.4941,
          "model_accuracy": 0.6151,
          "model_predictions": 1377,
          "avg_signed_return_bps": -1.6676
        },
        "3": {
          "regime_id": 3,
          "candles": 658,
          "trades": 177,
          "buys": 7,
          "sells": 170,
          "notional_usd": 2302.44,
          "fees_usd": 3.6839,
          "penalty_usd": 2.9884,
          "trade_rate": 0.269,
          "mean_stress": 0.3333,
          "mean_trend_score": -0.5984,
          "mean_dir_proba": 0.4724,
          "model_accuracy": 0.6156,
          "model_predictions": 346,
          "avg_signed_return_bps": 5.4317
        },
        "2": {
          "regime_id": 2,
          "candles": 1968,
          "trades": 501,
          "buys": 312,
          "sells": 189,
          "notional_usd": 6835.97,
          "fees_usd": 10.9376,
          "penalty_usd": 11.6656,
          "trade_rate": 0.2546,
          "mean_stress": 1.0,
          "mean_trend_score": -0.1268,
          "mean_dir_proba": 0.5115,
          "model_accuracy": 0.611,
          "model_predictions": 1540,
          "avg_signed_return_bps": -8.1045
        },
        "1": {
          "regime_id": 1,
          "candles": 1188,
          "trades": 6,
          "buys": 4,
          "sells": 2,
          "notional_usd": 83.89,
          "fees_usd": 0.1342,
          "penalty_usd": 0.0176,
          "trade_rate": 0.0051,
          "mean_stress": 0.0,
          "mean_trend_score": -0.0889,
          "mean_dir_proba": 0.4807,
          "model_accuracy": 0.6164,
          "model_predictions": 769,
          "avg_signed_return_bps": 3.3487
        }
      }
    },
    {
      "fold": 2,
      "train_rows": 12464,
      "test_rows": 5782,
      "train_end": 12464,
      "test_start": 12476,
      "test_end": 18258,
      "train_start_ts": "2026-01-07 03:00:00+00:00",
      "train_end_ts": "2026-02-19 09:35:00+00:00",
      "test_start_ts": "2026-02-19 10:40:00+00:00",
      "test_end_ts": "2026-03-11 12:25:00+00:00",
      "auc": 0.8001,
      "accuracy": 0.7186,
      "vol_mae": 0.002651,
      "vol_r2": 0.353,
      "sharpe_ratio": 4.737,
      "total_return_pct": 0.115,
      "max_drawdown_pct": -0.063,
      "total_trades": 542,
      "mtf_gate_fired": 1484,
      "regime_breakdown": {
        "2": {
          "regime_id": 2,
          "candles": 1529,
          "trades": 182,
          "buys": 155,
          "sells": 27,
          "notional_usd": 2464.81,
          "fees_usd": 3.9437,
          "penalty_usd": 2.5355,
          "trade_rate": 0.119,
          "mean_stress": 0.3333,
          "mean_trend_score": 0.0807,
          "mean_dir_proba": 0.5058,
          "model_accuracy": 0.6181,
          "model_predictions": 982,
          "avg_signed_return_bps": 5.0753
        },
        "3": {
          "regime_id": 3,
          "candles": 1545,
          "trades": 40,
          "buys": 15,
          "sells": 25,
          "notional_usd": 583.05,
          "fees_usd": 0.9329,
          "penalty_usd": 0.3867,
          "trade_rate": 0.0259,
          "mean_stress": 0.0,
          "mean_trend_score": -0.0223,
          "mean_dir_proba": 0.5053,
          "model_accuracy": 0.6424,
          "model_predictions": 1071,
          "avg_signed_return_bps": -5.7392
        },
        "0": {
          "regime_id": 0,
          "candles": 1825,
          "trades": 122,
          "buys": 10,
          "sells": 112,
          "notional_usd": 1716.51,
          "fees_usd": 2.7464,
          "penalty_usd": 1.4147,
          "trade_rate": 0.0668,
          "mean_stress": 0.6667,
          "mean_trend_score": -0.4019,
          "mean_dir_proba": 0.4964,
          "model_accuracy": 0.6192,
          "model_predictions": 1271,
          "avg_signed_return_bps": -0.6601
        },
        "1": {
          "regime_id": 1,
          "candles": 883,
          "trades": 198,
          "buys": 93,
          "sells": 105,
          "notional_usd": 2684.93,
          "fees_usd": 4.2959,
          "penalty_usd": 3.3672,
          "trade_rate": 0.2242,
          "mean_stress": 1.0,
          "mean_trend_score": -0.1178,
          "mean_dir_proba": 0.5034,
          "model_accuracy": 0.5854,
          "model_predictions": 714,
          "avg_signed_return_bps": -3.2179
        }
      }
    },
    {
      "fold": 3,
      "train_rows": 18246,
      "test_rows": 5782,
      "train_end": 18246,
      "test_start": 18258,
      "test_end": 24040,
      "train_start_ts": "2026-01-07 03:00:00+00:00",
      "train_end_ts": "2026-03-11 11:25:00+00:00",
      "test_start_ts": "2026-03-11 12:30:00+00:00",
      "test_end_ts": "2026-03-31 14:15:00+00:00",
      "auc": 0.8126,
      "accuracy": 0.7323,
      "vol_mae": 0.002445,
      "vol_r2": 0.3346,
      "sharpe_ratio": -6.509,
      "total_return_pct": -0.102,
      "max_drawdown_pct": -0.139,
      "total_trades": 331,
      "mtf_gate_fired": 1371,
      "regime_breakdown": {
        "0": {
          "regime_id": 0,
          "candles": 763,
          "trades": 101,
          "buys": 7,
          "sells": 94,
          "notional_usd": 1382.13,
          "fees_usd": 2.2114,
          "penalty_usd": 1.475,
          "trade_rate": 0.1324,
          "mean_stress": 0.6667,
          "mean_trend_score": -0.5763,
          "mean_dir_proba": 0.4665,
          "model_accuracy": 0.6133,
          "model_predictions": 375,
          "avg_signed_return_bps": -0.5791
        },
        "1": {
          "regime_id": 1,
          "candles": 2445,
          "trades": 77,
          "buys": 66,
          "sells": 11,
          "notional_usd": 1206.53,
          "fees_usd": 1.9305,
          "penalty_usd": 1.0256,
          "trade_rate": 0.0315,
          "mean_stress": 0.3333,
          "mean_trend_score": -0.0954,
          "mean_dir_proba": 0.4995,
          "model_accuracy": 0.6433,
          "model_predictions": 1472,
          "avg_signed_return_bps": -2.7169
        },
        "2": {
          "regime_id": 2,
          "candles": 1984,
          "trades": 28,
          "buys": 11,
          "sells": 17,
          "notional_usd": 373.84,
          "fees_usd": 0.5981,
          "penalty_usd": 0.3705,
          "trade_rate": 0.0141,
          "mean_stress": 0.0,
          "mean_trend_score": 0.0164,
          "mean_dir_proba": 0.5056,
          "model_accuracy": 0.6593,
          "model_predictions": 1177,
          "avg_signed_return_bps": 8.2101
        },
        "3": {
          "regime_id": 3,
          "candles": 590,
          "trades": 125,
          "buys": 84,
          "sells": 41,
          "notional_usd": 1505.62,
          "fees_usd": 2.409,
          "penalty_usd": 1.5157,
          "trade_rate": 0.2119,
          "mean_stress": 1.0,
          "mean_trend_score": -0.0201,
          "mean_dir_proba": 0.5161,
          "model_accuracy": 0.6075,
          "model_predictions": 451,
          "avg_signed_return_bps": -1.5199
        }
      }
    },
    {
      "fold": 4,
      "train_rows": 24028,
      "test_rows": 5782,
      "train_end": 24028,
      "test_start": 24040,
      "test_end": 29822,
      "train_start_ts": "2026-01-07 03:00:00+00:00",
      "train_end_ts": "2026-03-31 13:15:00+00:00",
      "test_start_ts": "2026-03-31 14:20:00+00:00",
      "test_end_ts": "2026-04-20 16:05:00+00:00",
      "auc": 0.8045,
      "accuracy": 0.7266,
      "vol_mae": 0.002087,
      "vol_r2": 0.4172,
      "sharpe_ratio": -0.136,
      "total_return_pct": -0.002,
      "max_drawdown_pct": -0.045,
      "total_trades": 242,
      "mtf_gate_fired": 1266,
      "regime_breakdown": {
        "2": {
          "regime_id": 2,
          "candles": 2616,
          "trades": 22,
          "buys": 12,
          "sells": 10,
          "notional_usd": 289.01,
          "fees_usd": 0.4624,
          "penalty_usd": 0.1528,
          "trade_rate": 0.0084,
          "mean_stress": 0.0,
          "mean_trend_score": 0.0127,
          "mean_dir_proba": 0.5002,
          "model_accuracy": 0.6514,
          "model_predictions": 1658,
          "avg_signed_return_bps": 6.7286
        },
        "0": {
          "regime_id": 0,
          "candles": 1863,
          "trades": 51,
          "buys": 2,
          "sells": 49,
          "notional_usd": 764.27,
          "fees_usd": 1.2228,
          "penalty_usd": 0.4944,
          "trade_rate": 0.0274,
          "mean_stress": 0.3333,
          "mean_trend_score": -0.4158,
          "mean_dir_proba": 0.5056,
          "model_accuracy": 0.6555,
          "model_predictions": 1042,
          "avg_signed_return_bps": -7.0111
        },
        "1": {
          "regime_id": 1,
          "candles": 484,
          "trades": 49,
          "buys": 9,
          "sells": 40,
          "notional_usd": 619.59,
          "fees_usd": 0.9913,
          "penalty_usd": 0.6786,
          "trade_rate": 0.1012,
          "mean_stress": 1.0,
          "mean_trend_score": -0.0721,
          "mean_dir_proba": 0.494,
          "model_accuracy": 0.634,
          "model_predictions": 377,
          "avg_signed_return_bps": -3.9515
        },
        "3": {
          "regime_id": 3,
          "candles": 819,
          "trades": 120,
          "buys": 105,
          "sells": 15,
          "notional_usd": 1622.54,
          "fees_usd": 2.5961,
          "penalty_usd": 1.6972,
          "trade_rate": 0.1465,
          "mean_stress": 0.6667,
          "mean_trend_score": 0.1198,
          "mean_dir_proba": 0.5544,
          "model_accuracy": 0.6203,
          "model_predictions": 503,
          "avg_signed_return_bps": -8.6999
        }
      }
    },
    {
      "fold": 5,
      "train_rows": 29810,
      "test_rows": 5786,
      "train_end": 29810,
      "test_start": 29822,
      "test_end": 35608,
      "train_start_ts": "2026-01-07 03:00:00+00:00",
      "train_end_ts": "2026-04-20 15:05:00+00:00",
      "test_start_ts": "2026-04-20 16:10:00+00:00",
      "test_end_ts": "2026-05-10 18:15:00+00:00",
      "auc": 0.7847,
      "accuracy": 0.705,
      "vol_mae": 0.001694,
      "vol_r2": 0.3027,
      "sharpe_ratio": 2.117,
      "total_return_pct": 0.027,
      "max_drawdown_pct": -0.047,
      "total_trades": 99,
      "mtf_gate_fired": 1388,
      "regime_breakdown": {
        "2": {
          "regime_id": 2,
          "candles": 1624,
          "trades": 0,
          "buys": 0,
          "sells": 0,
          "notional_usd": 0.0,
          "fees_usd": 0.0,
          "penalty_usd": 0.0,
          "trade_rate": 0.0,
          "mean_stress": 0.0,
          "mean_trend_score": 0.0541,
          "mean_dir_proba": 0.4825,
          "model_accuracy": 0.6529,
          "model_predictions": 942,
          "avg_signed_return_bps": 0.0
        },
        "3": {
          "regime_id": 3,
          "candles": 1432,
          "trades": 47,
          "buys": 45,
          "sells": 2,
          "notional_usd": 649.02,
          "fees_usd": 1.0384,
          "penalty_usd": 0.3904,
          "trade_rate": 0.0328,
          "mean_stress": 0.6667,
          "mean_trend_score": 0.1101,
          "mean_dir_proba": 0.5145,
          "model_accuracy": 0.6642,
          "model_predictions": 807,
          "avg_signed_return_bps": -0.993
        },
        "0": {
          "regime_id": 0,
          "candles": 2541,
          "trades": 33,
          "buys": 4,
          "sells": 29,
          "notional_usd": 417.16,
          "fees_usd": 0.6675,
          "penalty_usd": 0.3176,
          "trade_rate": 0.013,
          "mean_stress": 0.3333,
          "mean_trend_score": -0.3089,
          "mean_dir_proba": 0.5085,
          "model_accuracy": 0.6486,
          "model_predictions": 1474,
          "avg_signed_return_bps": 6.3415
        },
        "1": {
          "regime_id": 1,
          "candles": 189,
          "trades": 19,
          "buys": 0,
          "sells": 19,
          "notional_usd": 233.5,
          "fees_usd": 0.3736,
          "penalty_usd": 0.227,
          "trade_rate": 0.1005,
          "mean_stress": 1.0,
          "mean_trend_score": -0.1857,
          "mean_dir_proba": 0.4845,
          "model_accuracy": 0.6391,
          "model_predictions": 133,
          "avg_signed_return_bps": -9.7968
        }
      }
    }
  ],
  "summary": {
    "enabled": true,
    "fold_count": 6,
    "positive_sharpe_folds": 2,
    "positive_sharpe_last_6": 2,
    "passes_promotion_gate": false,
    "mean_sharpe": -1.8387,
    "median_sharpe": -1.5975,
    "mean_return_pct": -0.0508,
    "mean_auc": 0.7854
  }
}